{
  "users": [
    {
      "id": "f130",
      "username": "abdul_vajid",
      "password": "12345678",
      "email": "abdulvajid051@gmail.com",
      "cart": [
        {
          "id": "1",
          "name": "Men's Black Running",
          "price": 2000,
          "quantity": 14,
          "categories": "men",
          "images": "https://websitedemos.net/recycled-shoe-store-04/wp-content/uploads/sites/983/2021/11/recycled-shoe-product-image-005.jpg",
          "discription": "A stylish and comfortable black running shoe, perfect for daily use or sports. Provides excellent support and cushioning for outdoor activities."
        }
      ],
      "orders": [
        {
          "cartItems": [],
          "shippingAddress": {
            "fullName": "qweqrfonrq",
            "phone": "1234567890",
            "street": "ebgwnb[oqntqbbtrt",
            "city": "qetgqtgrtb",
            "state": "qetgtgwt",
            "zipCode": "123456"
          },
          "paymentDetails": {
            "cardNumber": "1234567890123456",
            "expiryDate": "12/34",
            "cvv": "123"
          },
          "orderDate": "2024-12-20T09:33:04.285Z"
        },
        {
          "cartItems": [
            {
              "id": "1",
              "name": "Men's Black Running",
              "price": 2000,
              "quantity": 3,
              "categories": "men",
              "images": "https://websitedemos.net/recycled-shoe-store-04/wp-content/uploads/sites/983/2021/11/recycled-shoe-product-image-005.jpg",
              "discription": "A stylish and comfortable black running shoe, perfect for daily use or sports. Provides excellent support and cushioning for outdoor activities."
            }
          ],
          "shippingAddress": {
            "fullName": "ajk",
            "phone": "1234567890",
            "street": "ewfWRL'KVNE",
            "city": "EFVQERV",
            "state": "QEFVREG",
            "zipCode": "1234556"
          },
          "paymentDetails": {
            "cardNumber": "1234567890098765",
            "expiryDate": "12/12",
            "cvv": "1213"
          },
          "orderDate": "2024-12-23T05:15:26.815Z"
        },
        {
          "cartItems": [
            {
              "id": "1",
              "name": "Men's Black Running",
              "price": 2000,
              "quantity": 1,
              "categories": "men",
              "images": "https://websitedemos.net/recycled-shoe-store-04/wp-content/uploads/sites/983/2021/11/recycled-shoe-product-image-005.jpg",
              "discription": "A stylish and comfortable black running shoe, perfect for daily use or sports. Provides excellent support and cushioning for outdoor activities."
            }
          ],
          "shippingAddress": {
            "fullName": "213",
            "phone": "1234123412",
            "street": "12345vetv",
            "city": "wtgvwrvvt",
            "state": "wvtrwr",
            "zipCode": "123453"
          },
          "paymentDetails": {
            "cardNumber": "12345678900987556",
            "expiryDate": "12/12",
            "cvv": "123"
          },
          "orderDate": "2024-12-23T05:37:56.638Z"
        },
        {
          "cartItems": [
            {
              "id": "1",
              "name": "Men's Black Running",
              "price": 2000,
              "quantity": 1,
              "categories": "men",
              "images": "https://websitedemos.net/recycled-shoe-store-04/wp-content/uploads/sites/983/2021/11/recycled-shoe-product-image-005.jpg",
              "discription": "A stylish and comfortable black running shoe, perfect for daily use or sports. Provides excellent support and cushioning for outdoor activities."
            }
          ],
          "shippingAddress": {
            "fullName": "qhiercqe",
            "phone": "1234567890",
            "street": "cjoerc2erf2cr",
            "city": "2rtv24",
            "state": "2rtvrtgvrt",
            "zipCode": "2134456"
          },
          "paymentDetails": {
            "cardNumber": "1234567891234567",
            "expiryDate": "12/12",
            "cvv": "112"
          },
          "orderDate": "2024-12-23T05:46:15.942Z"
        },
        {
          "cartItems": [
            {
              "id": "1",
              "name": "Men's Black Running",
              "price": 2000,
              "quantity": 5,
              "categories": "men",
              "images": "https://websitedemos.net/recycled-shoe-store-04/wp-content/uploads/sites/983/2021/11/recycled-shoe-product-image-005.jpg",
              "discription": "A stylish and comfortable black running shoe, perfect for daily use or sports. Provides excellent support and cushioning for outdoor activities."
            }
          ],
          "shippingAddress": {
            "fullName": "2eiryc",
            "phone": "1234567890",
            "street": "qejovncer",
            "city": "erjnp2e",
            "state": "wefj k",
            "zipCode": "123456"
          },
          "paymentDetails": {
            "cardNumber": "12345678079123456",
            "expiryDate": "12/21",
            "cvv": "213"
          },
          "orderDate": "2024-12-23T05:48:13.843Z"
        },
        {
          "cartItems": [
            {
              "id": "1",
              "name": "Men's Black Running",
              "price": 2000,
              "quantity": 1,
              "categories": "men",
              "images": "https://websitedemos.net/recycled-shoe-store-04/wp-content/uploads/sites/983/2021/11/recycled-shoe-product-image-005.jpg",
              "discription": "A stylish and comfortable black running shoe, perfect for daily use or sports. Provides excellent support and cushioning for outdoor activities."
            }
          ],
          "shippingAddress": {
            "fullName": "cwqjk",
            "phone": "wcej1",
            "street": "qecwererqc",
            "city": "qecr",
            "state": "qerfvq",
            "zipCode": "qerf"
          },
          "paymentDetails": {
            "cardNumber": "341565675432312543",
            "expiryDate": "1234",
            "cvv": "123"
          },
          "orderDate": "2024-12-23T06:00:42.128Z"
        },
        {
          "items": [
            {
              "id": "2",
              "name": "Men's Classic Blue",
              "price": 2999,
              "quantity": 1,
              "categories": "men",
              "images": "https://websitedemos.net/recycled-shoe-store-04/wp-content/uploads/sites/983/2021/11/recycled-shoe-product-image-019.jpg",
              "discription": "A timeless pair of classic blue sneakers, designed for comfort and durability. Ideal for casual wear or running errands."
            }
          ],
          "shippingAddress": {
            "fullName": "qwer",
            "phone": "12345678656",
            "street": "we'ltvn'wtro[rv",
            "city": "qerognqenjt",
            "state": "er]pgm]",
            "zipCode": "12345"
          },
          "paymentDetails": {
            "cardNumber": "123456890123456",
            "expiryDate": "12/32",
            "cvv": "123"
          },
          "orderDate": "2024-12-23T06:08:57.980Z"
        },
        {
          "items": [
            {
              "id": "1",
              "name": "Men's Black Running",
              "price": 2000,
              "quantity": 1,
              "categories": "men",
              "images": "https://websitedemos.net/recycled-shoe-store-04/wp-content/uploads/sites/983/2021/11/recycled-shoe-product-image-005.jpg",
              "discription": "A stylish and comfortable black running shoe, perfect for daily use or sports. Provides excellent support and cushioning for outdoor activities."
            }
          ],
          "shippingAddress": {
            "fullName": "qwfhpbr",
            "phone": "1234567899",
            "street": "o[4gtv",
            "city": "w[4o",
            "state": "24o[ng",
            "zipCode": "321`834"
          },
          "paymentDetails": {
            "cardNumber": "2134123412341234",
            "expiryDate": "12/21",
            "cvv": "234"
          },
          "orderDate": "2024-12-23T06:11:22.880Z"
        },
        {
          "cartItems": [
            {
              "id": "17",
              "name": "GNIST Pointed Toe Block Heel ",
              "price": 2699,
              "quantity": 1,
              "categories": "women",
              "images": "https://encrypted-tbn2.gstatic.com/shopping?q=tbn:ANd9GcQ6SbbdMOfSvvDVhNlsso92qM355RbkFRwa7zrUSWRgA1NSRs3Hh8aW4l6W0p86RKo9n8uAj2rcp7rujbZZsh6XBrmmmB_FHiLdBscbkeG1PKSwW7KotynoiA",
              "discription": "Sophisticated pointed-toe block heels that are perfect for work or evening events. Offers a sleek and fashionable silhouette with reliable comfort."
            }
          ],
          "shippingAddress": {
            "fullName": "qweffqfre",
            "phone": "1234567890",
            "street": "hfcsfivhihweqch",
            "city": "efvpperhiv",
            "state": "wrgtrtgv",
            "zipCode": "123454"
          },
          "paymentDetails": {
            "cardNumber": "1234567890123456",
            "expiryDate": "12/34",
            "cvv": "123"
          },
          "orderDate": "2024-12-23T06:28:31.862Z"
        },
        {
          "cartItems": [
            {
              "id": "3",
              "name": "Men's Classic Mint",
              "price": 3999,
              "quantity": 1,
              "categories": "men",
              "images": "https://websitedemos.net/recycled-shoe-store-04/wp-content/uploads/sites/983/2021/11/recycled-shoe-product-image-020.jpg",
              "discription": " A refreshing mint-colored sneaker that combines style and comfort, offering breathable material and flexible sole for active wear."
            }
          ],
          "shippingAddress": {
            "fullName": "qwerty",
            "phone": "1234567890",
            "street": "qwer",
            "city": "qwet",
            "state": "qwrt",
            "zipCode": "12345"
          },
          "paymentDetails": {
            "cardNumber": "1234567890123456",
            "expiryDate": "12/12",
            "cvv": "123"
          },
          "orderDate": "2024-12-23T06:32:59.859Z"
        },
        {
          "cartItems": [
            {
              "id": "1",
              "name": "Men's Black Running",
              "price": 2000,
              "quantity": 1,
              "categories": "men",
              "images": "https://websitedemos.net/recycled-shoe-store-04/wp-content/uploads/sites/983/2021/11/recycled-shoe-product-image-005.jpg",
              "discription": "A stylish and comfortable black running shoe, perfect for daily use or sports. Provides excellent support and cushioning for outdoor activities."
            }
          ],
          "shippingAddress": {
            "fullName": "qeruf",
            "phone": "1234567890",
            "street": "qreftqyerbuqer",
            "city": "qcpiewrvnqije",
            "state": "oi[r3f",
            "zipCode": "123456"
          },
          "paymentDetails": {
            "cardNumber": "1234567890123456",
            "expiryDate": "12/21",
            "cvv": "123"
          },
          "orderDate": "2024-12-23T06:42:00.737Z"
        },
        {
          "cartItems": [
            {
              "id": "1",
              "name": "Men's Black Running",
              "price": 2000,
              "quantity": 1,
              "categories": "men",
              "images": "https://websitedemos.net/recycled-shoe-store-04/wp-content/uploads/sites/983/2021/11/recycled-shoe-product-image-005.jpg",
              "discription": "A stylish and comfortable black running shoe, perfect for daily use or sports. Provides excellent support and cushioning for outdoor activities."
            }
          ],
          "shippingAddress": {
            "fullName": "qwew",
            "phone": "234566666667",
            "street": "wefv[oiqer",
            "city": "qeronv",
            "state": "qerjnf",
            "zipCode": "1234"
          },
          "paymentDetails": {
            "cardNumber": "1234567890123456",
            "expiryDate": "12/12",
            "cvv": "123"
          },
          "orderDate": "2024-12-23T06:45:05.468Z"
        },
        {
          "cartItems": [
            {
              "id": "7",
              "name": "Men's Moonstone Sneaker",
              "price": 2499,
              "quantity": 2,
              "categories": "men",
              "images": "https://websitedemos.net/recycled-shoe-store-04/wp-content/uploads/sites/983/2021/11/recycled-shoe-product-image-018.jpg",
              "discription": "Moonstone-themed sneakers with a sleek design, perfect for a trendy and athletic look. Great for both performance and style-conscious individuals."
            }
          ],
          "shippingAddress": {
            "fullName": "qewgrgt",
            "phone": "1234567890",
            "street": "wpejinrgviqegr",
            "city": "qer[ofn",
            "state": "qefmior",
            "zipCode": "123456"
          },
          "paymentDetails": {
            "cardNumber": "1234567890123456",
            "expiryDate": "12/34",
            "cvv": "123"
          },
          "orderDate": "2024-12-23T11:09:00.291Z"
        },
        {
          "cartItems": [
            {
              "id": "1",
              "name": "Men's Black Running",
              "price": 2000,
              "quantity": 1,
              "categories": "men",
              "images": "https://websitedemos.net/recycled-shoe-store-04/wp-content/uploads/sites/983/2021/11/recycled-shoe-product-image-005.jpg",
              "discription": "A stylish and comfortable black running shoe, perfect for daily use or sports. Provides excellent support and cushioning for outdoor activities."
            }
          ],
          "shippingAddress": {
            "fullName": "ouyqber",
            "phone": "1234567890",
            "street": "qwprie",
            "city": "qejvi",
            "state": "qerph",
            "zipCode": "123456"
          },
          "paymentDetails": {
            "cardNumber": "1234567890123456",
            "expiryDate": "12/34",
            "cvv": "123"
          },
          "orderDate": "2024-12-23T12:43:48.752Z"
        },
        {
          "cartItems": [
            {
              "id": "1",
              "name": "Men's Black Running",
              "price": 2000,
              "quantity": 1,
              "categories": "men",
              "images": "https://websitedemos.net/recycled-shoe-store-04/wp-content/uploads/sites/983/2021/11/recycled-shoe-product-image-005.jpg",
              "discription": "A stylish and comfortable black running shoe, perfect for daily use or sports. Provides excellent support and cushioning for outdoor activities."
            },
            {
              "id": "2",
              "name": "Men's Classic Blue",
              "price": 2999,
              "quantity": 1,
              "categories": "men",
              "images": "https://websitedemos.net/recycled-shoe-store-04/wp-content/uploads/sites/983/2021/11/recycled-shoe-product-image-019.jpg",
              "discription": "A timeless pair of classic blue sneakers, designed for comfort and durability. Ideal for casual wear or running errands."
            },
            {
              "id": "4",
              "name": "Men's Red Running",
              "price": 1999,
              "quantity": 1,
              "categories": "men",
              "images": "https://websitedemos.net/recycled-shoe-store-04/wp-content/uploads/sites/983/2021/11/recycled-shoe-product-image-006.jpg",
              "discription": "Bold and bright red running shoes designed for athletes. Offers a lightweight feel with a cushioned sole for impact protection during intense workouts."
            }
          ],
          "shippingAddress": {
            "fullName": "qweqerv",
            "phone": "1234567890",
            "street": "qervjtr",
            "city": "qr[nfjenv",
            "state": "qerpnvgwrt",
            "zipCode": "123456"
          },
          "paymentDetails": {
            "cardNumber": "1234567890123456",
            "expiryDate": "12/34",
            "cvv": "123"
          },
          "orderDate": "2024-12-23T12:47:37.916Z"
        },
        {
          "cartItems": [
            {
              "id": "1",
              "name": "Men's Black Running",
              "price": 2000,
              "quantity": 1,
              "categories": "men",
              "images": "https://websitedemos.net/recycled-shoe-store-04/wp-content/uploads/sites/983/2021/11/recycled-shoe-product-image-005.jpg",
              "discription": "A stylish and comfortable black running shoe, perfect for daily use or sports. Provides excellent support and cushioning for outdoor activities."
            },
            {
              "id": "2",
              "name": "Men's Classic Blue",
              "price": 2999,
              "quantity": 1,
              "categories": "men",
              "images": "https://websitedemos.net/recycled-shoe-store-04/wp-content/uploads/sites/983/2021/11/recycled-shoe-product-image-019.jpg",
              "discription": "A timeless pair of classic blue sneakers, designed for comfort and durability. Ideal for casual wear or running errands."
            },
            {
              "id": "4",
              "name": "Men's Red Running",
              "price": 1999,
              "quantity": 1,
              "categories": "men",
              "images": "https://websitedemos.net/recycled-shoe-store-04/wp-content/uploads/sites/983/2021/11/recycled-shoe-product-image-006.jpg",
              "discription": "Bold and bright red running shoes designed for athletes. Offers a lightweight feel with a cushioned sole for impact protection during intense workouts."
            }
          ],
          "shippingAddress": {
            "fullName": "eoqchb",
            "phone": "1234567890",
            "street": "qwefdec",
            "city": "wercvae",
            "state": "vqervfq12345",
            "zipCode": "1235"
          },
          "paymentDetails": {
            "cardNumber": "1234567890123456",
            "expiryDate": "12/34",
            "cvv": "123"
          },
          "orderDate": "2024-12-23T12:52:02.025Z"
        },
        {
          "cartItems": [
            {
              "id": "1",
              "name": "Men's Black Running",
              "price": 2000,
              "quantity": 1,
              "categories": "men",
              "images": "https://websitedemos.net/recycled-shoe-store-04/wp-content/uploads/sites/983/2021/11/recycled-shoe-product-image-005.jpg",
              "discription": "A stylish and comfortable black running shoe, perfect for daily use or sports. Provides excellent support and cushioning for outdoor activities."
            },
            {
              "id": "2",
              "name": "Men's Classic Blue",
              "price": 2999,
              "quantity": 1,
              "categories": "men",
              "images": "https://websitedemos.net/recycled-shoe-store-04/wp-content/uploads/sites/983/2021/11/recycled-shoe-product-image-019.jpg",
              "discription": "A timeless pair of classic blue sneakers, designed for comfort and durability. Ideal for casual wear or running errands."
            },
            {
              "id": "4",
              "name": "Men's Red Running",
              "price": 1999,
              "quantity": 1,
              "categories": "men",
              "images": "https://websitedemos.net/recycled-shoe-store-04/wp-content/uploads/sites/983/2021/11/recycled-shoe-product-image-006.jpg",
              "discription": "Bold and bright red running shoes designed for athletes. Offers a lightweight feel with a cushioned sole for impact protection during intense workouts."
            }
          ],
          "shippingAddress": {
            "fullName": "qaswedrfgthyju",
            "phone": "1234567890",
            "street": "xecrvtbynu",
            "city": "dtfvygbu",
            "state": "dcvtfgyb",
            "zipCode": "1232345"
          },
          "paymentDetails": {
            "cardNumber": "1234567890123456",
            "expiryDate": "12/12",
            "cvv": "123"
          },
          "orderDate": "2024-12-23T12:56:59.804Z"
        },
        {
          "cartItems": [
            {
              "id": "5",
              "name": "Men's Navy Running",
              "price": 2499,
              "quantity": 1,
              "categories": "men",
              "images": "https://websitedemos.net/recycled-shoe-store-04/wp-content/uploads/sites/983/2021/11/recycled-shoe-product-image-008.jpg",
              "discription": "Stylish navy running shoes with a modern design. Great for both fitness enthusiasts and casual wear with a comfortable, supportive fit."
            }
          ],
          "shippingAddress": {
            "fullName": "qwertyui",
            "phone": "1234567890",
            "street": "qawsedrftgyhuji",
            "city": "aexscdrvftbgy",
            "state": "drctfvgyb",
            "zipCode": "123456"
          },
          "paymentDetails": {
            "cardNumber": "1234567890123456",
            "expiryDate": "12/12",
            "cvv": "123"
          },
          "orderDate": "2024-12-23T13:15:31.843Z"
        },
        {
          "cartItems": [
            {
              "id": "2",
              "name": "Men's Classic Blue",
              "price": 2999,
              "quantity": 1,
              "categories": "men",
              "images": "https://websitedemos.net/recycled-shoe-store-04/wp-content/uploads/sites/983/2021/11/recycled-shoe-product-image-019.jpg",
              "discription": "A timeless pair of classic blue sneakers, designed for comfort and durability. Ideal for casual wear or running errands."
            }
          ],
          "shippingAddress": {
            "fullName": "qwertyu",
            "phone": "1234567890",
            "street": "rdctfv",
            "city": "xrcdbg",
            "state": "ertyui",
            "zipCode": "123456"
          },
          "paymentDetails": {
            "cardNumber": "1234567890123456",
            "expiryDate": "12/34",
            "cvv": "1234"
          },
          "orderDate": "2024-12-23T13:19:28.399Z"
        },
        {
          "cartItems": [
            {
              "id": "1",
              "name": "Men's Black Running",
              "price": 2000,
              "quantity": 1,
              "categories": "men",
              "images": "https://websitedemos.net/recycled-shoe-store-04/wp-content/uploads/sites/983/2021/11/recycled-shoe-product-image-005.jpg",
              "discription": "A stylish and comfortable black running shoe, perfect for daily use or sports. Provides excellent support and cushioning for outdoor activities."
            },
            {
              "id": "11",
              "name": "Campus Women Kim Walkig Shoe",
              "price": 1999,
              "quantity": 1,
              "categories": "women",
              "images": "https://encrypted-tbn2.gstatic.com/shopping?q=tbn:ANd9GcSHDahNK_7KCP2LLqnAxu7jfyCnAMmjKaasFFnGje92UrxUOqQswRfNqnwCZQot_KBdU1_Qhi8BYzG7iluLXFEu8Tnxf9BHoLTg3zQswYfr5UbQDZZldZmn",
              "discription": "A comfortable and stylish walking shoe for women. Provides excellent arch support and cushioning, perfect for long walks or daily wear."
            }
          ],
          "shippingAddress": {
            "fullName": "utrtqd",
            "phone": "1426537687980",
            "street": "9ygcuyqer",
            "city": "wefvonvw",
            "state": "qerferv1",
            "zipCode": "13342"
          },
          "paymentDetails": {
            "cardNumber": "1234567890`13245",
            "expiryDate": "12/32",
            "cvv": "123"
          },
          "orderDate": "2024-12-24T05:04:35.902Z"
        },
        {
          "cartItems": [
            {
              "id": "1",
              "name": "Men's Black Running",
              "price": 2000,
              "quantity": 2,
              "categories": "men",
              "images": "https://websitedemos.net/recycled-shoe-store-04/wp-content/uploads/sites/983/2021/11/recycled-shoe-product-image-005.jpg",
              "discription": "A stylish and comfortable black running shoe, perfect for daily use or sports. Provides excellent support and cushioning for outdoor activities."
            }
          ],
          "shippingAddress": {
            "fullName": "dew6tgw",
            "phone": "1234567890",
            "street": "fsggrd",
            "city": "tye5g",
            "state": "dgfeg",
            "zipCode": "123456"
          },
          "paymentDetails": {
            "cardNumber": "1234567890123456",
            "expiryDate": "12/12",
            "cvv": "123"
          },
          "orderDate": "2024-12-24T14:03:05.983Z"
        }
      ],
      "address": {
        "fullName": "dew6tgw",
        "phone": "1234567890",
        "street": "fsggrd",
        "city": "tye5g",
        "state": "dgfeg",
        "zipCode": "123456"
      }
    },
    {
      "id": "187f",
      "username": "admin",
      "password": "987654321",
      "email": "vajidkp8@gmail.com"
    }
  ],
  "products": [
    {
      "id": "1",
      "name": "Men's Black Running",
      "price": 2000,
      "quantity": 14,
      "categories": "men",
      "images": "https://websitedemos.net/recycled-shoe-store-04/wp-content/uploads/sites/983/2021/11/recycled-shoe-product-image-005.jpg",
      "discription": "A stylish and comfortable black running shoe, perfect for daily use or sports. Provides excellent support and cushioning for outdoor activities."
    },
    {
      "id": "2",
      "name": "Men's Classic Blue",
      "price": 2999,
      "quantity": 14,
      "categories": "men",
      "images": "https://websitedemos.net/recycled-shoe-store-04/wp-content/uploads/sites/983/2021/11/recycled-shoe-product-image-019.jpg",
      "discription": "A timeless pair of classic blue sneakers, designed for comfort and durability. Ideal for casual wear or running errands."
    },
    {
      "id": "3",
      "name": "Men's Classic Mint",
      "price": 3999,
      "quantity": 12,
      "categories": "men",
      "images": "https://websitedemos.net/recycled-shoe-store-04/wp-content/uploads/sites/983/2021/11/recycled-shoe-product-image-020.jpg",
      "discription": " A refreshing mint-colored sneaker that combines style and comfort, offering breathable material and flexible sole for active wear."
    },
    {
      "id": "4",
      "name": "Men's Red Running",
      "price": 1999,
      "quantity": 11,
      "categories": "men",
      "images": "https://websitedemos.net/recycled-shoe-store-04/wp-content/uploads/sites/983/2021/11/recycled-shoe-product-image-006.jpg",
      "discription": "Bold and bright red running shoes designed for athletes. Offers a lightweight feel with a cushioned sole for impact protection during intense workouts."
    },
    {
      "id": "5",
      "name": "Men's Navy Running",
      "price": 2499,
      "quantity": 11,
      "categories": "men",
      "images": "https://websitedemos.net/recycled-shoe-store-04/wp-content/uploads/sites/983/2021/11/recycled-shoe-product-image-008.jpg",
      "discription": "Stylish navy running shoes with a modern design. Great for both fitness enthusiasts and casual wear with a comfortable, supportive fit."
    },
    {
      "id": "6",
      "name": "Men's Green Running",
      "price": 1599,
      "quantity": 15,
      "categories": "men",
      "images": "https://websitedemos.net/recycled-shoe-store-04/wp-content/uploads/sites/983/2021/11/recycled-shoe-product-image-007.jpg",
      "discription": "A vibrant green pair of running shoes that blends performance and style. Lightweight and designed to keep you moving effortlessly."
    },
    {
      "id": "7",
      "name": "Men's Moonstone Sneaker",
      "price": 2499,
      "quantity": 12,
      "categories": "men",
      "images": "https://websitedemos.net/recycled-shoe-store-04/wp-content/uploads/sites/983/2021/11/recycled-shoe-product-image-018.jpg",
      "discription": "Moonstone-themed sneakers with a sleek design, perfect for a trendy and athletic look. Great for both performance and style-conscious individuals."
    },
    {
      "id": "8",
      "name": "Men's Earth-Tone Sneaker",
      "price": 2999,
      "quantity": 14,
      "categories": "men",
      "images": "https://websitedemos.net/recycled-shoe-store-04/wp-content/uploads/sites/983/2021/11/recycled-shoe-product-image-017.jpg",
      "discription": "Earth-tone sneakers that are both functional and fashionable. Suitable for outdoor enthusiasts and those who enjoy versatile footwear."
    },
    {
      "id": "9",
      "name": "Sparx SI 170 Runnig Shoe",
      "price": 2999,
      "quantity": 13,
      "categories": "women",
      "images": "https://encrypted-tbn0.gstatic.com/shopping?q=tbn:ANd9GcSjYMcLaygJ3LYqQ_7Js89Z5aaK3xClsbQOMIMGjWp6veP09OG-h2v0-S-wLNdvgRKf-oiIsNWOmP5ACeKXlH9FLH5h2OVwFmKmughq46qMANRUEu1lsLuUBA",
      "discription": "A high-performance running shoe from Sparx with a sleek design, great for casual and athletic wear. Provides excellent grip and cushioning for running."
    },
    {
      "id": "10",
      "name": "Leather ballet pumps",
      "price": 1500,
      "quantity": 15,
      "categories": "women",
      "images": "//lp2.hm.com/hmgoepprod?set=format%5Bwebp%5D%2Cquality%5B79%5D%2Csource%5B%2F26%2Fcc%2F26ccd57b07bb57632ebb83eb93bf834bb3fa7f9a.jpg%5D%2Corigin%5Bdam%5D%2Ccategory%5Bladies_premium_selection_shoes%5D%2Ctype%5BDESCRIPTIVESTILLLIFE%5D%2Cres%5Bm%5D%2Chmver%5B2%5D&call=url%5Bfile%3A%2Fproduct%2Fmain%5D",
      "discription": " Elegant and versatile leather ballet flats for women. These shoes provide a chic look and comfortable fit, perfect for formal or casual occasions."
    },
    {
      "id": "11",
      "name": "Campus Women Kim Walkig Shoe",
      "price": 1999,
      "quantity": 20,
      "categories": "women",
      "images": "https://encrypted-tbn2.gstatic.com/shopping?q=tbn:ANd9GcSHDahNK_7KCP2LLqnAxu7jfyCnAMmjKaasFFnGje92UrxUOqQswRfNqnwCZQot_KBdU1_Qhi8BYzG7iluLXFEu8Tnxf9BHoLTg3zQswYfr5UbQDZZldZmn",
      "discription": "A comfortable and stylish walking shoe for women. Provides excellent arch support and cushioning, perfect for long walks or daily wear."
    },
    {
      "id": "12",
      "name": "Vendoze Casual ",
      "price": 3499,
      "quantity": 33,
      "categories": "women",
      "images": "https://encrypted-tbn3.gstatic.com/shopping?q=tbn:ANd9GcRYtXwPqA4lZKybxhUBEDvhdFJC4csqAvdfPIPCpnFyPbGAqunCX-_tkT4xlp9w1aIYqXtXMUJZV7Zfz1I4cYFegcFE3f63Gd3cv5QhLiIZErNkryGqHpwj",
      "discription": "Vendoze's casual shoes offer an easy-to-wear, comfortable option for everyday use. Stylish and practical for relaxed outings and casual events."
    },
    {
      "id": "13",
      "name": "Sandak Slip-on Casual",
      "price": 1599,
      "quantity": 22,
      "categories": "women",
      "images": "https://encrypted-tbn3.gstatic.com/shopping?q=tbn:ANd9GcQgg66EXemUrYghmFsvoBkRK1iaXuyCrRHzt9W7J8h8dB6nJCgvHmPFfVyYZr9TUy8JZmYr8_rSIVLiv7xavB6YJGs04fc062M68E5q1E56zaZ4imAAh0aQ",
      "discription": "Sandak’s slip-on casual shoes for women provide effortless style and comfort, perfect for on-the-go wear. Ideal for a laid-back lifestyle."
    },
    {
      "id": "15",
      "name": "Red Tape Textured ",
      "price": 3999,
      "quantity": 12,
      "categories": "women",
      "images": "https://encrypted-tbn3.gstatic.com/shopping?q=tbn:ANd9GcRr-vR2G7H5GjtLdy_FqRk5KPSB_e3FAohvs8PMXIMbRa1MTH-215-S66EM7hQPJUKcZygVGUk86G0vRvzM_kvI_g7x0_tV-TsnJazEyzDbdmPlep_l3Aej",
      "discription": "Textured red tape heels that combine modern design with a classic feel. Perfect for office wear or formal events."
    },
    {
      "id": "16",
      "name": "freddie Hot Space Block Heel",
      "price": 2999,
      "quantity": 12,
      "categories": "women",
      "images": "https://encrypted-tbn3.gstatic.com/shopping?q=tbn:ANd9GcQOIakd5eT-It0ENKX1bg9MhHbQhXZYwds-5lk3gEoUn8lqdS4HH7D2UoOsuTV9RuF7ncCn-HYJ53Vc_XjZAI8EyySINIPzN3dHaaFdp9lybxHnuJ3Dxtky3A",
      "discription": "Chic block heels with a modern design, offering comfort without sacrificing style. Ideal for a fashionable look with lasting comfort."
    },
    {
      "id": "17",
      "name": "GNIST Pointed Toe Block Heel ",
      "price": 2699,
      "quantity": 14,
      "categories": "women",
      "images": "https://encrypted-tbn2.gstatic.com/shopping?q=tbn:ANd9GcQ6SbbdMOfSvvDVhNlsso92qM355RbkFRwa7zrUSWRgA1NSRs3Hh8aW4l6W0p86RKo9n8uAj2rcp7rujbZZsh6XBrmmmB_FHiLdBscbkeG1PKSwW7KotynoiA",
      "discription": "Sophisticated pointed-toe block heels that are perfect for work or evening events. Offers a sleek and fashionable silhouette with reliable comfort."
    }
  ]
}